{
  "document_id": "CS_006",
  "source_files": ["data/raw_images/DataSet/cast study/CS_006.jpeg"],
  "page_count": 1,
  "document": {
    "document_type": "case_study",
    "form_version": "new",
    "page_side": "front",
    "case_number": null,
    "research_date": "2025/12/19",
    "source_entity": null
  },
  "office": {
    "directorate": "المنوفية",
    "administration": "شبين الكوم",
    "social_unit": null,
    "researcher_name": null,
    "requesting_entity": null,
    "research_purpose": null
  },
  "applicant": {
    "full_name": "صبحة سامي عبد الحميد الديب",
    "national_id": null,
    "insurance_number": null,
    "age": 40,
    "gender": "أنثى",
    "phone": null,
    "address": null,
    "governorate": "المنوفية",
    "district": null,
    "marital_status": "أرملة",
    "education_status": "دبلوم تجاري",
    "employment_status": "لا يعمل",
    "health_status": "جيدة"
  },
  "family_members": [
    {"row_index": 1, "name": "صبحة سامي عبد الحميد الديب", "relationship": "الأم", "age": 40, "national_id": null, "marital_status": "أرملة", "education_status": "دبلوم تجاري", "employment_status": "لا يعمل", "health_status": "جيدة", "notes": null},
    {"row_index": 2, "name": "مريم هشام يوسف عبد الحميد", "relationship": "ابنة", "age": 17, "national_id": null, "marital_status": "طالبة", "education_status": "الثالث الثانوي", "employment_status": "لا يعمل", "health_status": "جيدة", "notes": null},
    {"row_index": 3, "name": "سراج هشام يوسف عبد الحميد", "relationship": "ابن", "age": 13, "national_id": null, "marital_status": "طالب", "education_status": "الثاني الإعدادي", "employment_status": "لا يعمل", "health_status": "جيدة", "notes": null},
    {"row_index": 4, "name": "أحمد هشام يوسف عبد الحميد", "relationship": "ابن", "age": 6, "national_id": null, "marital_status": "طالب", "education_status": "أول ابتدائي", "employment_status": "لا يعمل", "health_status": "جيدة", "notes": null}
  ],
  "housing": {
    "type": null,
    "ownership": null,
    "area": null,
    "rooms_count": null,
    "rent_value": null,
    "independence": null,
    "water_source": null,
    "electricity": null,
    "appliances_condition": null
  },
  "assets": {"properties": null},
  "social_assessment": {
    "family_social_status": null,
    "health_notes": null,
    "economic_status": null,
    "family_needs": null,
    "researcher_summary": null
  },
  "checkbox_answers": [
    {"section": "بيانات أولية", "question": "النوع", "answer": "أنثى", "checked": true, "confidence": "medium"},
    {"section": "الحالة الاجتماعية", "question": "الحالة الاجتماعية", "answer": "أرملة", "checked": true, "confidence": "medium"},
    {"section": "نوع السكن", "question": "نوع السكن", "answer": "ملك", "checked": true, "confidence": "low"},
    {"section": "المرافق", "question": "الكهرباء", "answer": "نعم", "checked": true, "confidence": "medium"}
  ],
  "signatures": {
    "researcher_name": null,
    "unit_manager_name": null,
    "stamp_present": false
  },
  "uncertain_fields": ["applicant.national_id", "family_members.national_id", "checkbox_answers"],
  "review_required": false,
  "review_notes": ["new front page; national ID digits are not confidently readable"]
}
